psf2flf/__init__.py
psf2flf/__main__.py
psf2flf/main.py
psf2flf/utils.py
psf2flf/font/__init__.py
psf2flf/font/font.py
psf2flf/font/fontdir.py
psf2flf/font/typeface.py
psf2flf/reader/__init__.py
psf2flf/reader/psf.py
psf2flf/reader/reader.py
psf2flf/writer/__init__.py
psf2flf/writer/flf.py
psf2flf/writer/writer.py
psf2flf-0.0.4.dist-info/entry_points.txt
psf2flf-0.0.4.dist-info/licenses/LICENSE.md
psf2flf-0.0.4.dist-info/WHEEL
psf2flf-0.0.4.dist-info/METADATA
psf2flf-0.0.4.dist-info/RECORD
